{
  "profiles": [
      {
        "name": "Kristi Centinaro",
        "shortname": "kristi",
        "title": "I build sexy websites.",
        "portrait_url": "/images/kristi_photo.jpg",
        "resume_url": "/docs/KristiCentinaro-Resume2012.pdf",
        "social_links": [
          {
            "name": "twitter",
            "title": "Kristi on Twitter",
            "url": "//twitter.com/theresnobox"
          },{
            "name": "google",
            "title": "Kristi's Google+ Profile",
            "url": "//plus.google.com/u/0/105851997129401536120/"
          },{
            "name": "github",
            "title": "Samples on Github",
            "url": "//github.com/tnbKristi"
          },{
            "name": "deviantart",
            "title": "Kristi on Deviantart",
            "url": "//inkjetcanvas.deviantart.com"
          }
        ]
      },{
        "name": "Bill Centinaro",
        "shortname": "bill",
        "title": "I make great websites work.",
        "portrait_url": "/images/bill_photo.jpg",
        "resume_url": "/docs/BillCentinaro-Resume2012.pdf",
        "social_links": [
          {
            "name": "twitter",
            "title": "Bill on Twitter",
            "url": "//twitter.com/bcentinaro"
          },{
            "name": "google",
            "title": "Bill's Google+ Profile",
            "url": "//plus.google.com/u/0/117447149473400301135/"
          },{
            "name": "github",
            "title": "Check out my Open Source Projects!",
            "url": "//github.com/tnbBill"
          }
        ]
    }
  ],
  "questions": [
      {
        "question": "What do you like doing best?",
        "answer": {
          "kristi": "I'm happiest when I'm building dynamic, engaging experiences for people on the web.",
          "bill": "I like being the man behind the curtain."
        }
      },
      {
        "question": "Favorite tools of the trade",
        "answer": {
          "kristi": "Javascript, HTML5, CSS3",
          "bill": ""
        }
      },
      {
        "question": "What are your favorite development tools?",
        "answer": {
          "kristi": "I love doing front-end development for anything built in Ruby, Python, and lately, NodeJs. I also prefer to work with SASS over plain CSS.",
          "bill": ""
        }
      },
      {
        "question": "What have you been working on lately?",
        "answer": {
          "kristi": "At work, I have been building mobile-friendly responsive survey \"widgets\". These are used by thousands of surveyers daily at YouGov across many countries!",
          "bill": ""
        }
      },
      {
        "question": "What do you do for fun?",
        "answer": {
          "kristi": "I just started CrossFit! I like to work out, play video games (Guild Wars 2!), and <a href=\"//inkjetcanvas.deviantart.com\" target=\"_blank\">paint.</a>",
          "bill": ""
        }
      },
      {
        "question": "Any side projects?",
        "answer": {
          "kristi": "Bill and I have been building a CMS Network for Small Businesses. We have some very enthusiastic clients that have helped us test. It's going great so far!",
          "bill": ""
        }
      }
  ],
  "projects": [
    {
      "name": "Red Headed Angel",
      "description": "A fun remix of a very old picture I painted.",
      "thumbnail": "/images/projects/kristi_art_1.png", 
      "url": "//inkjetcanvas.deviantart.com/gallery/#/d4k6e7t",
      "owner": ["kristi"]
    }, {
      "name": "\"Kiss Kiss\"",
      "description": "Check out the Timelapse Video of this painting!",
      "thumbnail": "/images/projects/kristi_art_2.png", 
      "url": "//vimeo.com/18414753",
      "owner": ["kristi"]
    }, {
      "name": "Image Gallery Widget",
      "description": "A Work-In-Progress UI for use in our CMS - a way for users to build a dynamic image gallery.",
      "thumbnail": "/images/projects/code_blank.png", 
      "url": "/imageGallery",
      "owner": ["kristi"]
    }, {
      "name": "YouGov Research MENA",
      "description": "I love this site because with one stylesheet it supports Arabic and English. SASS-based style architecture makes this process very simple.",
      "thumbnail": "/images/projects/kristi_web_1.png", 
      "url": "//research.mena.yougov.com/ar/",
      "owner": ["kristi"]
    }, {
      "name": "DropWallet (Gem)",
      "description": "A RubyGem created to connect to DropWallet’s API, intended to provide Active Record / Active Model feel for connecting to the dropwallet API for DropWallet’s various ruby projects.",
      "thumbnail": "/images/projects/code_blank.png", 
      "url": "https://rubygems.org/gems/dropwallet",
      "owner": ["bill"]
    }, {
      "name": "Checkout Experience",
      "description": "DropWallet’s Checkout experience for 3rd party sites, currently slated for deployment to several magazine publisher’s web sites. A responsive interface designed to work with mobile, tablet, and desktop. Written in Ruby, connected to the internal DropWallet API for data access. Ultimately intended to replace multiple dated projects. (<a href=\"https://customer.dropwallet.net/\" target=\"_blank\">link</a> and <a href=\"https://m.dropwallet.net/\" target=\"_blank\">link</a>)",
      "thumbnail": "/images/projects/code_blank.png", 
      "url": "http://checkout.dropwallet.net",
      "owner": ["bill"]
    }, {
      "name": "DropWallet API router",
      "description": "A Node.JS project designed to route API requests to various endpoints, making them appear as a single system. Built in Cache and Security, keeps as much of the load off the end points as possible.", 
      "thumbnail": "/images/projects/code_blank.png", 
      "url": "",
      "owner": ["bill"]
    }, {
      "name": "Cartography",
      "description": "A simple sitemap generator, designed to build a sitemap XML string... intended to be stored in a database. (A requirement for our Unboxed Network CMS)", 
      "thumbnail": "/images/projects/code_blank.png", 
      "url": "https://github.com/TNBBill/cartography",
      "owner": ["bill"]
    }, {
      "name": "MultiStripe",
      "description": "An API wrapper for <a href=\"stripe.com\" target=\"_blank\">Stripe</a> which allows the API key of a request to be specified in a request by request basis while being thread safe.", 
      "thumbnail": "/images/projects/code_blank.png", 
      "url": "https://github.com/TNBBill/multistripe",
      "owner": ["bill"]
    }

  ]
    
}